{
  "facts": {
    "user_name": "abhiyank",
    "age": "20",
    "friend_name": "rahul",
    "likes": "coding and gaming",
    "remembered": "my exam is on 15th april"
  },
  "learned": [
    {
      "what": "user_name: abhiyank",
      "category": "personal",
      "learned_at": "2026-04-02 22:45"
    },
    {
      "what": "age: 20",
      "category": "personal",
      "learned_at": "2026-04-02 22:45"
    },
    {
      "what": "friend_name: rahul",
      "category": "people",
      "learned_at": "2026-04-02 22:45"
    },
    {
      "what": "likes: coding and gaming",
      "category": "preference",
      "learned_at": "2026-04-02 22:45"
    },
    {
      "what": "remembered: my exam is on 15th april",
      "category": "explicit_remember",
      "learned_at": "2026-04-02 22:45"
    }
  ],
  "usage_log": [],
  "command_frequency": {},
  "time_patterns": {},
  "topic_frequency": {
    "coding": 1,
    "studies": 1
  },
  "owner": "Abhiyank",
  "owner_protected": true,
  "mood_history": [
    {
      "mood": "happy",
      "timestamp": "2026-04-02 22:45"
    }
  ],
  "current_mood": "happy"
}